{
	"$schema": "http://schema.management.azure.com/schemas/2015-01-01/deploymentTemplate.json#",
	"contentVersion": "1.0.0.0",
	"parameters": {
		"factoryName": {
			"type": "string",
			"metadata": "Data Factory name",
			"defaultValue": "appfactory20231031"
		},
		"appvmserver_password": {
			"type": "secureString",
			"metadata": "Secure string for 'password' of 'appvmserver'"
		},
		"appvmserver_properties_typeProperties_host": {
			"type": "string",
			"defaultValue": "D:\\nginx-1.24.0\\logs"
		},
		"appvmserver_properties_typeProperties_userId": {
			"type": "string",
			"defaultValue": "appuser"
		}
	},
	"variables": {
		"factoryId": "[concat('Microsoft.DataFactory/factories/', parameters('factoryName'))]"
	},
	"resources": [
		{
			"name": "[concat(parameters('factoryName'), '/jsonobject_table')]",
			"type": "Microsoft.DataFactory/factories/datasets",
			"apiVersion": "2018-06-01",
			"properties": {
				"linkedServiceName": {
					"referenceName": "appdblinkedservice",
					"type": "LinkedServiceReference"
				},
				"annotations": [],
				"type": "AzureSqlTable",
				"schema": [
					{
						"name": "CustomerID",
						"type": "int",
						"precision": 10
					},
					{
						"name": "CustomerName",
						"type": "varchar"
					},
					{
						"name": "Registered",
						"type": "bit"
					},
					{
						"name": "Courses",
						"type": "varchar"
					},
					{
						"name": "Mobile",
						"type": "varchar"
					},
					{
						"name": "City",
						"type": "varchar"
					}
				],
				"typeProperties": {
					"schema": "dbo",
					"table": "Customercourse_object"
				}
			},
			"dependsOn": []
		},
		{
			"name": "[concat(parameters('factoryName'), '/logdatajsontable')]",
			"type": "Microsoft.DataFactory/factories/datasets",
			"apiVersion": "2018-06-01",
			"properties": {
				"linkedServiceName": {
					"referenceName": "adf to db",
					"type": "LinkedServiceReference"
				},
				"annotations": [],
				"type": "AzureSqlTable",
				"schema": [
					{
						"name": "Correlationid",
						"type": "nvarchar"
					},
					{
						"name": "Operationname",
						"type": "nvarchar"
					},
					{
						"name": "Status",
						"type": "nvarchar"
					},
					{
						"name": "Eventcategory",
						"type": "nvarchar"
					},
					{
						"name": "Level",
						"type": "nvarchar"
					},
					{
						"name": "Time",
						"type": "datetime",
						"precision": 23,
						"scale": 3
					},
					{
						"name": "Subscription",
						"type": "nvarchar"
					},
					{
						"name": "Eventinitiatedby",
						"type": "nvarchar"
					},
					{
						"name": "Resourcetype",
						"type": "nvarchar"
					},
					{
						"name": "Resourcegroup",
						"type": "nvarchar"
					},
					{
						"name": "Resource",
						"type": "nvarchar"
					}
				],
				"typeProperties": {
					"schema": "dbo",
					"table": "logdatajsontable"
				}
			},
			"dependsOn": []
		},
		{
			"name": "[concat(parameters('factoryName'), '/objectjson')]",
			"type": "Microsoft.DataFactory/factories/datasets",
			"apiVersion": "2018-06-01",
			"properties": {
				"linkedServiceName": {
					"referenceName": "csv to ddb",
					"type": "LinkedServiceReference"
				},
				"annotations": [],
				"type": "Json",
				"typeProperties": {
					"location": {
						"type": "AzureBlobFSLocation",
						"fileName": "customer_2.json",
						"fileSystem": "json"
					}
				},
				"schema": {
					"type": "object",
					"properties": {
						"customerid": {
							"type": "integer"
						},
						"customername": {
							"type": "string"
						},
						"registered": {
							"type": "boolean"
						},
						"courses": {
							"type": "array",
							"items": {
								"type": "string"
							}
						},
						"details": {
							"type": "object",
							"properties": {
								"mobile": {
									"type": "string"
								},
								"city": {
									"type": "string"
								}
							}
						}
					}
				}
			},
			"dependsOn": []
		},
		{
			"name": "[concat(parameters('factoryName'), '/partitiontable')]",
			"type": "Microsoft.DataFactory/factories/datasets",
			"apiVersion": "2018-06-01",
			"properties": {
				"linkedServiceName": {
					"referenceName": "adf to db",
					"type": "LinkedServiceReference"
				},
				"annotations": [],
				"type": "AzureSqlTable",
				"schema": [
					{
						"name": "Correlationid",
						"type": "varchar"
					},
					{
						"name": "Operationname",
						"type": "varchar"
					},
					{
						"name": "Status",
						"type": "varchar"
					},
					{
						"name": "Eventcategory",
						"type": "varchar"
					},
					{
						"name": "Level",
						"type": "varchar"
					},
					{
						"name": "Time",
						"type": "varchar"
					},
					{
						"name": "Subscription",
						"type": "varchar"
					},
					{
						"name": "Eventinitiatedby",
						"type": "varchar"
					},
					{
						"name": "Resourcetype",
						"type": "varchar"
					},
					{
						"name": "Resourcegroup",
						"type": "varchar"
					},
					{
						"name": "Resource",
						"type": "varchar"
					}
				],
				"typeProperties": {
					"schema": "dbo",
					"table": "logdata_parquet_partition"
				}
			},
			"dependsOn": []
		},
		{
			"name": "[concat(parameters('factoryName'), '/salesorderdetalsLS')]",
			"type": "Microsoft.DataFactory/factories/datasets",
			"apiVersion": "2018-06-01",
			"properties": {
				"linkedServiceName": {
					"referenceName": "appdblinkedservice",
					"type": "LinkedServiceReference"
				},
				"annotations": [],
				"type": "AzureSqlTable",
				"schema": [
					{
						"name": "SalesOrderID",
						"type": "int",
						"precision": 10
					},
					{
						"name": "SalesOrderDetailID",
						"type": "int",
						"precision": 10
					},
					{
						"name": "OrderQty",
						"type": "smallint",
						"precision": 5
					},
					{
						"name": "ProductID",
						"type": "int",
						"precision": 10
					},
					{
						"name": "UnitPrice",
						"type": "money",
						"precision": 19,
						"scale": 4
					},
					{
						"name": "UnitPriceDiscount",
						"type": "money",
						"precision": 19,
						"scale": 4
					},
					{
						"name": "LineTotal",
						"type": "decimal",
						"precision": 38,
						"scale": 6
					},
					{
						"name": "rowguid",
						"type": "uniqueidentifier"
					},
					{
						"name": "ModifiedDate",
						"type": "datetime",
						"precision": 23,
						"scale": 3
					}
				],
				"typeProperties": {
					"schema": "SalesLT",
					"table": "SalesOrderDetail"
				}
			},
			"dependsOn": []
		},
		{
			"name": "[concat(parameters('factoryName'), '/salesorderheaderLS')]",
			"type": "Microsoft.DataFactory/factories/datasets",
			"apiVersion": "2018-06-01",
			"properties": {
				"linkedServiceName": {
					"referenceName": "appdblinkedservice",
					"type": "LinkedServiceReference"
				},
				"annotations": [],
				"type": "AzureSqlTable",
				"schema": [
					{
						"name": "SalesOrderID",
						"type": "int",
						"precision": 10
					},
					{
						"name": "RevisionNumber",
						"type": "tinyint",
						"precision": 3
					},
					{
						"name": "OrderDate",
						"type": "datetime",
						"precision": 23,
						"scale": 3
					},
					{
						"name": "DueDate",
						"type": "datetime",
						"precision": 23,
						"scale": 3
					},
					{
						"name": "ShipDate",
						"type": "datetime",
						"precision": 23,
						"scale": 3
					},
					{
						"name": "Status",
						"type": "tinyint",
						"precision": 3
					},
					{
						"name": "OnlineOrderFlag",
						"type": "bit"
					},
					{
						"name": "SalesOrderNumber",
						"type": "nvarchar"
					},
					{
						"name": "PurchaseOrderNumber",
						"type": "nvarchar"
					},
					{
						"name": "AccountNumber",
						"type": "nvarchar"
					},
					{
						"name": "CustomerID",
						"type": "int",
						"precision": 10
					},
					{
						"name": "ShipToAddressID",
						"type": "int",
						"precision": 10
					},
					{
						"name": "BillToAddressID",
						"type": "int",
						"precision": 10
					},
					{
						"name": "ShipMethod",
						"type": "nvarchar"
					},
					{
						"name": "CreditCardApprovalCode",
						"type": "varchar"
					},
					{
						"name": "SubTotal",
						"type": "money",
						"precision": 19,
						"scale": 4
					},
					{
						"name": "TaxAmt",
						"type": "money",
						"precision": 19,
						"scale": 4
					},
					{
						"name": "Freight",
						"type": "money",
						"precision": 19,
						"scale": 4
					},
					{
						"name": "TotalDue",
						"type": "money",
						"precision": 19,
						"scale": 4
					},
					{
						"name": "Comment",
						"type": "nvarchar"
					},
					{
						"name": "rowguid",
						"type": "uniqueidentifier"
					},
					{
						"name": "ModifiedDate",
						"type": "datetime",
						"precision": 23,
						"scale": 3
					}
				],
				"typeProperties": {
					"schema": "SalesLT",
					"table": "SalesOrderHeader"
				}
			},
			"dependsOn": []
		},
		{
			"name": "[concat(parameters('factoryName'), '/webcsv')]",
			"type": "Microsoft.DataFactory/factories/datasets",
			"apiVersion": "2018-06-01",
			"properties": {
				"linkedServiceName": {
					"referenceName": "csv to ddb",
					"type": "LinkedServiceReference"
				},
				"annotations": [],
				"type": "DelimitedText",
				"typeProperties": {
					"location": {
						"type": "AzureBlobFSLocation",
						"fileName": "dummy.txt",
						"fileSystem": "webdata"
					},
					"columnDelimiter": ",",
					"escapeChar": "\\",
					"firstRowAsHeader": true,
					"quoteChar": "\""
				},
				"schema": []
			},
			"dependsOn": []
		},
		{
			"name": "[concat(parameters('factoryName'), '/appvmserver')]",
			"type": "Microsoft.DataFactory/factories/linkedServices",
			"apiVersion": "2018-06-01",
			"properties": {
				"annotations": [],
				"type": "FileServer",
				"typeProperties": {
					"host": "[parameters('appvmserver_properties_typeProperties_host')]",
					"userId": "[parameters('appvmserver_properties_typeProperties_userId')]",
					"password": {
						"type": "SecureString",
						"value": "[parameters('appvmserver_password')]"
					}
				},
				"connectVia": {
					"referenceName": "appvmhostedRuntime",
					"type": "IntegrationRuntimeReference"
				}
			},
			"dependsOn": []
		},
		{
			"name": "[concat(parameters('factoryName'), '/COPYTOPARQUET')]",
			"type": "Microsoft.DataFactory/factories/pipelines",
			"apiVersion": "2018-06-01",
			"properties": {
				"activities": [
					{
						"name": "Copy PARQUET",
						"type": "Copy",
						"dependsOn": [],
						"policy": {
							"timeout": "0.12:00:00",
							"retry": 0,
							"retryIntervalInSeconds": 30,
							"secureOutput": false,
							"secureInput": false
						},
						"userProperties": [],
						"typeProperties": {
							"source": {
								"type": "DelimitedTextSource",
								"storeSettings": {
									"type": "AzureBlobFSReadSettings",
									"recursive": true,
									"enablePartitionDiscovery": false
								},
								"formatSettings": {
									"type": "DelimitedTextReadSettings"
								}
							},
							"sink": {
								"type": "ParquetSink",
								"storeSettings": {
									"type": "AzureBlobFSWriteSettings"
								},
								"formatSettings": {
									"type": "ParquetWriteSettings"
								}
							},
							"enableStaging": false,
							"translator": {
								"type": "TabularTranslator",
								"mappings": [
									{
										"source": {
											"name": "Correlation id",
											"type": "String",
											"physicalType": "String"
										},
										"sink": {
											"name": "Correlationid",
											"physicalType": "UTF8"
										}
									},
									{
										"source": {
											"name": "Operation name",
											"type": "String",
											"physicalType": "String"
										},
										"sink": {
											"name": "Operationname",
											"physicalType": "UTF8"
										}
									},
									{
										"source": {
											"name": "Status",
											"type": "String",
											"physicalType": "String"
										},
										"sink": {
											"name": "Status",
											"type": "String",
											"physicalType": "UTF8"
										}
									},
									{
										"source": {
											"name": "Event category",
											"type": "String",
											"physicalType": "String"
										},
										"sink": {
											"name": "Eventcategory",
											"physicalType": "UTF8"
										}
									},
									{
										"source": {
											"name": "Level",
											"type": "String",
											"physicalType": "String"
										},
										"sink": {
											"name": "Level",
											"type": "String",
											"physicalType": "UTF8"
										}
									},
									{
										"source": {
											"name": "Time",
											"type": "DateTime",
											"physicalType": "String"
										},
										"sink": {
											"name": "Time",
											"type": "String",
											"physicalType": "UTF8"
										}
									},
									{
										"source": {
											"name": "Subscription",
											"type": "String",
											"physicalType": "String"
										},
										"sink": {
											"name": "Subscription",
											"type": "String",
											"physicalType": "UTF8"
										}
									},
									{
										"source": {
											"name": "Event initiated by",
											"type": "String",
											"physicalType": "String"
										},
										"sink": {
											"name": "Eventinitiatedby",
											"physicalType": "UTF8"
										}
									},
									{
										"source": {
											"name": "Resource type",
											"type": "String",
											"physicalType": "String"
										},
										"sink": {
											"name": "Resourcetype",
											"physicalType": "UTF8"
										}
									},
									{
										"source": {
											"name": "Resource group",
											"type": "String",
											"physicalType": "String"
										},
										"sink": {
											"name": "Resourcegroup",
											"physicalType": "UTF8"
										}
									},
									{
										"source": {
											"name": "Resource",
											"type": "String",
											"physicalType": "String"
										},
										"sink": {
											"name": "Resource",
											"type": "String",
											"physicalType": "UTF8"
										}
									}
								],
								"typeConversion": true,
								"typeConversionSettings": {
									"allowDataTruncation": true,
									"treatBooleanAsNumber": false
								}
							}
						},
						"inputs": [
							{
								"referenceName": "SourceDataset_90z",
								"type": "DatasetReference",
								"parameters": {}
							}
						],
						"outputs": [
							{
								"referenceName": "LOGDATA_PARQUET",
								"type": "DatasetReference",
								"parameters": {}
							}
						]
					},
					{
						"name": "Copy parq to db",
						"type": "Copy",
						"dependsOn": [
							{
								"activity": "Copy PARQUET",
								"dependencyConditions": [
									"Succeeded"
								]
							}
						],
						"policy": {
							"timeout": "0.12:00:00",
							"retry": 0,
							"retryIntervalInSeconds": 30,
							"secureOutput": false,
							"secureInput": false
						},
						"userProperties": [],
						"typeProperties": {
							"source": {
								"type": "ParquetSource",
								"storeSettings": {
									"type": "AzureBlobFSReadSettings",
									"recursive": true,
									"wildcardFileName": "*.parquet",
									"enablePartitionDiscovery": false
								},
								"formatSettings": {
									"type": "ParquetReadSettings"
								}
							},
							"sink": {
								"type": "AzureSqlSink",
								"writeBehavior": "insert",
								"sqlWriterUseTableLock": false
							},
							"enableStaging": false,
							"translator": {
								"type": "TabularTranslator",
								"mappings": [
									{
										"source": {
											"name": "Correlationid",
											"type": "String",
											"physicalType": "UTF8"
										},
										"sink": {
											"name": "Correlationid",
											"type": "String",
											"physicalType": "nvarchar"
										}
									},
									{
										"source": {
											"name": "Operationname",
											"type": "String",
											"physicalType": "UTF8"
										},
										"sink": {
											"name": "Operationname",
											"type": "String",
											"physicalType": "nvarchar"
										}
									},
									{
										"source": {
											"name": "Status",
											"type": "String",
											"physicalType": "UTF8"
										},
										"sink": {
											"name": "Status",
											"type": "String",
											"physicalType": "nvarchar"
										}
									},
									{
										"source": {
											"name": "Eventcategory",
											"type": "String",
											"physicalType": "UTF8"
										},
										"sink": {
											"name": "Eventcategory",
											"type": "String",
											"physicalType": "nvarchar"
										}
									},
									{
										"source": {
											"name": "Level",
											"type": "String",
											"physicalType": "UTF8"
										},
										"sink": {
											"name": "Level",
											"type": "String",
											"physicalType": "nvarchar"
										}
									},
									{
										"source": {
											"name": "Time",
											"type": "DateTime",
											"physicalType": "INT96"
										},
										"sink": {
											"name": "Time",
											"type": "DateTime",
											"physicalType": "datetime"
										}
									},
									{
										"source": {
											"name": "Subscription",
											"type": "String",
											"physicalType": "UTF8"
										},
										"sink": {
											"name": "Subscription",
											"type": "String",
											"physicalType": "nvarchar"
										}
									},
									{
										"source": {
											"name": "Eventinitiatedby",
											"type": "String",
											"physicalType": "UTF8"
										},
										"sink": {
											"name": "Eventinitiatedby",
											"type": "String",
											"physicalType": "nvarchar"
										}
									},
									{
										"source": {
											"name": "Resourcetype",
											"type": "String",
											"physicalType": "UTF8"
										},
										"sink": {
											"name": "Resourcetype",
											"type": "String",
											"physicalType": "nvarchar"
										}
									},
									{
										"source": {
											"name": "Resourcegroup",
											"type": "String",
											"physicalType": "UTF8"
										},
										"sink": {
											"name": "Resourcegroup",
											"type": "String",
											"physicalType": "nvarchar"
										}
									},
									{
										"source": {
											"name": "Resource",
											"type": "String",
											"physicalType": "UTF8"
										},
										"sink": {
											"name": "Resource",
											"type": "String",
											"physicalType": "nvarchar"
										}
									}
								],
								"typeConversion": true,
								"typeConversionSettings": {
									"allowDataTruncation": true,
									"treatBooleanAsNumber": false
								}
							}
						},
						"inputs": [
							{
								"referenceName": "LOGDATA_PARQUET",
								"type": "DatasetReference",
								"parameters": {}
							}
						],
						"outputs": [
							{
								"referenceName": "AzureSqlTableparquet",
								"type": "DatasetReference",
								"parameters": {}
							}
						]
					},
					{
						"name": "partitioncopy",
						"type": "Copy",
						"dependsOn": [
							{
								"activity": "Copy parq to db",
								"dependencyConditions": [
									"Succeeded"
								]
							}
						],
						"policy": {
							"timeout": "0.12:00:00",
							"retry": 0,
							"retryIntervalInSeconds": 30,
							"secureOutput": false,
							"secureInput": false
						},
						"userProperties": [],
						"typeProperties": {
							"source": {
								"type": "AzureSqlSource",
								"queryTimeout": "02:00:00",
								"partitionOption": "PhysicalPartitionsOfTable"
							},
							"sink": {
								"type": "AzureSqlSink",
								"writeBehavior": "insert",
								"sqlWriterUseTableLock": false
							},
							"enableStaging": false,
							"translator": {
								"type": "TabularTranslator",
								"typeConversion": true,
								"typeConversionSettings": {
									"allowDataTruncation": true,
									"treatBooleanAsNumber": false
								}
							}
						},
						"inputs": [
							{
								"referenceName": "AzureSqlTableparquet",
								"type": "DatasetReference",
								"parameters": {}
							}
						],
						"outputs": [
							{
								"referenceName": "partitiontable",
								"type": "DatasetReference",
								"parameters": {}
							}
						]
					}
				],
				"policy": {
					"elapsedTimeMetric": {}
				},
				"annotations": [],
				"lastPublishTime": "2023-12-04T09:03:51Z"
			},
			"dependsOn": [
				"[concat(variables('factoryId'), '/datasets/partitiontable')]"
			]
		},
		{
			"name": "[concat(parameters('factoryName'), '/CopyPipeline_ezj')]",
			"type": "Microsoft.DataFactory/factories/pipelines",
			"apiVersion": "2018-06-01",
			"properties": {
				"activities": [
					{
						"name": "Copy_parqview",
						"type": "Copy",
						"dependsOn": [],
						"policy": {
							"timeout": "0.12:00:00",
							"retry": 0,
							"retryIntervalInSeconds": 30,
							"secureOutput": false,
							"secureInput": false
						},
						"userProperties": [
							{
								"name": "Source",
								"value": "."
							},
							{
								"name": "Destination",
								"value": "dbo.parquet_view"
							}
						],
						"typeProperties": {
							"source": {
								"type": "AzureSqlSource",
								"sqlReaderQuery": "select top 100 * from  dbo.logdata_parquet",
								"partitionOption": "None"
							},
							"sink": {
								"type": "AzureSqlSink",
								"tableOption": "autoCreate"
							},
							"enableStaging": false,
							"validateDataConsistency": false,
							"translator": {
								"type": "TabularTranslator",
								"mappings": [
									{
										"source": {
											"name": "Correlationid",
											"type": "String",
											"physicalType": "nvarchar"
										},
										"sink": {
											"name": "Correlationid",
											"type": "String"
										}
									},
									{
										"source": {
											"name": "Operationname",
											"type": "String",
											"physicalType": "nvarchar"
										},
										"sink": {
											"name": "Operationname",
											"type": "String"
										}
									},
									{
										"source": {
											"name": "Status",
											"type": "String",
											"physicalType": "nvarchar"
										},
										"sink": {
											"name": "Status",
											"type": "String"
										}
									},
									{
										"source": {
											"name": "Eventcategory",
											"type": "String",
											"physicalType": "nvarchar"
										},
										"sink": {
											"name": "Eventcategory",
											"type": "String"
										}
									},
									{
										"source": {
											"name": "Level",
											"type": "String",
											"physicalType": "nvarchar"
										},
										"sink": {
											"name": "Level",
											"type": "String"
										}
									},
									{
										"source": {
											"name": "Time",
											"type": "DateTime",
											"physicalType": "datetime"
										},
										"sink": {
											"name": "Time",
											"type": "DateTime"
										}
									},
									{
										"source": {
											"name": "Subscription",
											"type": "String",
											"physicalType": "nvarchar"
										},
										"sink": {
											"name": "Subscription",
											"type": "String"
										}
									},
									{
										"source": {
											"name": "Eventinitiatedby",
											"type": "String",
											"physicalType": "nvarchar"
										},
										"sink": {
											"name": "Eventinitiatedby",
											"type": "String"
										}
									},
									{
										"source": {
											"name": "Resourcetype",
											"type": "String",
											"physicalType": "nvarchar"
										},
										"sink": {
											"name": "Resourcetype",
											"type": "String"
										}
									},
									{
										"source": {
											"name": "Resourcegroup",
											"type": "String",
											"physicalType": "nvarchar"
										},
										"sink": {
											"name": "Resourcegroup",
											"type": "String"
										}
									},
									{
										"source": {
											"name": "Resource",
											"type": "String",
											"physicalType": "nvarchar"
										},
										"sink": {
											"name": "Resource",
											"type": "String"
										}
									}
								],
								"typeConversion": true,
								"typeConversionSettings": {
									"allowDataTruncation": true,
									"treatBooleanAsNumber": false
								}
							}
						},
						"inputs": [
							{
								"referenceName": "SourceDataset_ezj",
								"type": "DatasetReference",
								"parameters": {}
							}
						],
						"outputs": [
							{
								"referenceName": "DestinationDataset_ezj",
								"type": "DatasetReference",
								"parameters": {}
							}
						]
					}
				],
				"policy": {
					"elapsedTimeMetric": {}
				},
				"annotations": [],
				"lastPublishTime": "2023-12-03T21:36:06Z"
			},
			"dependsOn": []
		},
		{
			"name": "[concat(parameters('factoryName'), '/CopyPipeline_y85')]",
			"type": "Microsoft.DataFactory/factories/pipelines",
			"apiVersion": "2018-06-01",
			"properties": {
				"activities": [
					{
						"name": "Copy_y85",
						"type": "Copy",
						"dependsOn": [],
						"policy": {
							"timeout": "0.12:00:00",
							"retry": 0,
							"retryIntervalInSeconds": 30,
							"secureOutput": false,
							"secureInput": false
						},
						"userProperties": [
							{
								"name": "Source",
								"value": "csv//Log.csv"
							},
							{
								"name": "Destination",
								"value": "dbo.Log"
							}
						],
						"typeProperties": {
							"source": {
								"type": "DelimitedTextSource",
								"storeSettings": {
									"type": "AzureBlobFSReadSettings",
									"recursive": true,
									"enablePartitionDiscovery": false
								},
								"formatSettings": {
									"type": "DelimitedTextReadSettings",
									"skipLineCount": 0
								}
							},
							"sink": {
								"type": "AzureSqlSink",
								"tableOption": "autoCreate"
							},
							"enableStaging": false,
							"validateDataConsistency": false,
							"translator": {
								"type": "TabularTranslator",
								"mappings": [
									{
										"source": {
											"name": "Correlation id",
											"type": "String",
											"physicalType": "String"
										},
										"sink": {
											"name": "Correlation id",
											"type": "String"
										}
									},
									{
										"source": {
											"name": "Operation name",
											"type": "String",
											"physicalType": "String"
										},
										"sink": {
											"name": "Operation name",
											"type": "String"
										}
									},
									{
										"source": {
											"name": "Status",
											"type": "String",
											"physicalType": "String"
										},
										"sink": {
											"name": "Status",
											"type": "String"
										}
									},
									{
										"source": {
											"name": "Event category",
											"type": "String",
											"physicalType": "String"
										},
										"sink": {
											"name": "Event category",
											"type": "String"
										}
									},
									{
										"source": {
											"name": "Level",
											"type": "String",
											"physicalType": "String"
										},
										"sink": {
											"name": "Level",
											"type": "String"
										}
									},
									{
										"source": {
											"name": "Time",
											"type": "String",
											"physicalType": "String"
										},
										"sink": {
											"name": "Time",
											"type": "String"
										}
									},
									{
										"source": {
											"name": "Subscription",
											"type": "String",
											"physicalType": "String"
										},
										"sink": {
											"name": "Subscription",
											"type": "String"
										}
									},
									{
										"source": {
											"name": "Event initiated by",
											"type": "String",
											"physicalType": "String"
										},
										"sink": {
											"name": "Event initiated by",
											"type": "String"
										}
									},
									{
										"source": {
											"name": "Resource type",
											"type": "String",
											"physicalType": "String"
										},
										"sink": {
											"name": "Resource type",
											"type": "String"
										}
									},
									{
										"source": {
											"name": "Resource group",
											"type": "String",
											"physicalType": "String"
										},
										"sink": {
											"name": "Resource group",
											"type": "String"
										}
									},
									{
										"source": {
											"name": "Resource",
											"type": "String",
											"physicalType": "String"
										},
										"sink": {
											"name": "Resource",
											"type": "String"
										}
									}
								],
								"typeConversion": true,
								"typeConversionSettings": {
									"allowDataTruncation": true,
									"treatBooleanAsNumber": false
								}
							}
						},
						"inputs": [
							{
								"referenceName": "SourceDataset_y85",
								"type": "DatasetReference",
								"parameters": {}
							}
						],
						"outputs": [
							{
								"referenceName": "DestinationDataset_y85",
								"type": "DatasetReference",
								"parameters": {}
							}
						]
					}
				],
				"policy": {
					"elapsedTimeMetric": {}
				},
				"annotations": [],
				"lastPublishTime": "2023-12-01T20:26:43Z"
			},
			"dependsOn": []
		},
		{
			"name": "[concat(parameters('factoryName'), '/ForEach')]",
			"type": "Microsoft.DataFactory/factories/pipelines",
			"apiVersion": "2018-06-01",
			"properties": {
				"activities": [
					{
						"name": "ForEachCustFile",
						"type": "ForEach",
						"dependsOn": [
							{
								"activity": "GetMetadata",
								"dependencyConditions": [
									"Succeeded"
								]
							}
						],
						"userProperties": [],
						"typeProperties": {
							"items": {
								"value": "@activity('GetMetadata').output.childItems",
								"type": "Expression"
							},
							"activities": [
								{
									"name": "CopyEachdata",
									"type": "Copy",
									"dependsOn": [],
									"policy": {
										"timeout": "0.12:00:00",
										"retry": 0,
										"retryIntervalInSeconds": 30,
										"secureOutput": false,
										"secureInput": false
									},
									"userProperties": [],
									"typeProperties": {
										"source": {
											"type": "DelimitedTextSource",
											"storeSettings": {
												"type": "AzureBlobFSReadSettings",
												"recursive": true,
												"enablePartitionDiscovery": false
											},
											"formatSettings": {
												"type": "DelimitedTextReadSettings"
											}
										},
										"sink": {
											"type": "AzureSqlSink",
											"writeBehavior": "insert",
											"sqlWriterUseTableLock": false
										},
										"enableStaging": false,
										"translator": {
											"type": "TabularTranslator",
											"mappings": [
												{
													"source": {
														"name": "CustomerID",
														"type": "String",
														"physicalType": "String"
													},
													"sink": {
														"name": "CustomerID",
														"type": "Int32",
														"physicalType": "int"
													}
												},
												{
													"source": {
														"name": "NameStyle",
														"type": "String",
														"physicalType": "String"
													},
													"sink": {
														"name": "NameStyle",
														"type": "Boolean",
														"physicalType": "bit"
													}
												},
												{
													"source": {
														"name": "Title",
														"type": "String",
														"physicalType": "String"
													},
													"sink": {
														"name": "Title",
														"type": "String",
														"physicalType": "nvarchar"
													}
												},
												{
													"source": {
														"name": "FirstName",
														"type": "String",
														"physicalType": "String"
													},
													"sink": {
														"name": "FirstName",
														"type": "String",
														"physicalType": "nvarchar"
													}
												},
												{
													"source": {
														"name": "MiddleName",
														"type": "String",
														"physicalType": "String"
													},
													"sink": {
														"name": "MiddleName",
														"type": "String",
														"physicalType": "nvarchar"
													}
												},
												{
													"source": {
														"name": "LastName",
														"type": "String",
														"physicalType": "String"
													},
													"sink": {
														"name": "LastName",
														"type": "String",
														"physicalType": "nvarchar"
													}
												},
												{
													"source": {
														"name": "Suffix",
														"type": "String",
														"physicalType": "String"
													},
													"sink": {
														"name": "Suffix",
														"type": "String",
														"physicalType": "nvarchar"
													}
												},
												{
													"source": {
														"name": "CompanyName",
														"type": "String",
														"physicalType": "String"
													},
													"sink": {
														"name": "CompanyName",
														"type": "String",
														"physicalType": "nvarchar"
													}
												},
												{
													"source": {
														"name": "SalesPerson",
														"type": "String",
														"physicalType": "String"
													},
													"sink": {
														"name": "SalesPerson",
														"type": "String",
														"physicalType": "nvarchar"
													}
												},
												{
													"source": {
														"name": "EmailAddress",
														"type": "String",
														"physicalType": "String"
													},
													"sink": {
														"name": "EmailAddress",
														"type": "String",
														"physicalType": "nvarchar"
													}
												},
												{
													"source": {
														"name": "Phone",
														"type": "String",
														"physicalType": "String"
													},
													"sink": {
														"name": "Phone",
														"type": "String",
														"physicalType": "nvarchar"
													}
												},
												{
													"source": {
														"name": "PasswordHash",
														"type": "String",
														"physicalType": "String"
													},
													"sink": {
														"name": "PasswordHash",
														"type": "String",
														"physicalType": "varchar"
													}
												},
												{
													"source": {
														"name": "PasswordSalt",
														"type": "String",
														"physicalType": "String"
													},
													"sink": {
														"name": "PasswordSalt",
														"type": "String",
														"physicalType": "varchar"
													}
												},
												{
													"source": {
														"name": "rowguid",
														"type": "String",
														"physicalType": "String"
													},
													"sink": {
														"name": "rowguid",
														"type": "Guid",
														"physicalType": "uniqueidentifier"
													}
												}
											],
											"typeConversion": true,
											"typeConversionSettings": {
												"allowDataTruncation": true,
												"treatBooleanAsNumber": false
											}
										}
									},
									"inputs": [
										{
											"referenceName": "DelimitedText",
											"type": "DatasetReference",
											"parameters": {
												"filename": {
													"value": "@item().Name",
													"type": "Expression"
												}
											}
										}
									],
									"outputs": [
										{
											"referenceName": "AzureSqlTable4",
											"type": "DatasetReference",
											"parameters": {}
										}
									]
								}
							]
						}
					},
					{
						"name": "GetMetadata",
						"type": "GetMetadata",
						"dependsOn": [],
						"policy": {
							"timeout": "0.12:00:00",
							"retry": 0,
							"retryIntervalInSeconds": 30,
							"secureOutput": false,
							"secureInput": false
						},
						"userProperties": [],
						"typeProperties": {
							"dataset": {
								"referenceName": "getcsvlist",
								"type": "DatasetReference",
								"parameters": {}
							},
							"fieldList": [
								"childItems"
							],
							"storeSettings": {
								"type": "AzureBlobFSReadSettings",
								"recursive": true,
								"enablePartitionDiscovery": false
							},
							"formatSettings": {
								"type": "DelimitedTextReadSettings"
							}
						}
					}
				],
				"policy": {
					"elapsedTimeMetric": {}
				},
				"annotations": []
			},
			"dependsOn": []
		},
		{
			"name": "[concat(parameters('factoryName'), '/ForEach_copy1')]",
			"type": "Microsoft.DataFactory/factories/pipelines",
			"apiVersion": "2018-06-01",
			"properties": {
				"activities": [
					{
						"name": "ForEachCustFile",
						"type": "ForEach",
						"dependsOn": [
							{
								"activity": "GetMetadata",
								"dependencyConditions": [
									"Succeeded"
								]
							}
						],
						"userProperties": [],
						"typeProperties": {
							"items": {
								"value": "@activity('GetMetadata').output.childItems",
								"type": "Expression"
							},
							"activities": [
								{
									"name": "CopyEachdata",
									"type": "Copy",
									"dependsOn": [],
									"policy": {
										"timeout": "0.12:00:00",
										"retry": 0,
										"retryIntervalInSeconds": 30,
										"secureOutput": false,
										"secureInput": false
									},
									"userProperties": [],
									"typeProperties": {
										"source": {
											"type": "DelimitedTextSource",
											"storeSettings": {
												"type": "AzureBlobFSReadSettings",
												"recursive": true,
												"enablePartitionDiscovery": false
											},
											"formatSettings": {
												"type": "DelimitedTextReadSettings"
											}
										},
										"sink": {
											"type": "AzureSqlSink",
											"writeBehavior": "insert",
											"sqlWriterUseTableLock": false
										},
										"enableStaging": false,
										"translator": {
											"type": "TabularTranslator",
											"mappings": [
												{
													"source": {
														"name": "CustomerID",
														"type": "String",
														"physicalType": "String"
													},
													"sink": {
														"name": "CustomerID",
														"type": "Int32",
														"physicalType": "int"
													}
												},
												{
													"source": {
														"name": "NameStyle",
														"type": "String",
														"physicalType": "String"
													},
													"sink": {
														"name": "NameStyle",
														"type": "String",
														"physicalType": "nvarchar"
													}
												},
												{
													"source": {
														"name": "Title",
														"type": "String",
														"physicalType": "String"
													},
													"sink": {
														"name": "Title",
														"type": "String",
														"physicalType": "nvarchar"
													}
												},
												{
													"source": {
														"name": "FirstName",
														"type": "String",
														"physicalType": "String"
													},
													"sink": {
														"name": "FirstName",
														"type": "String",
														"physicalType": "nvarchar"
													}
												},
												{
													"source": {
														"name": "MiddleName",
														"type": "String",
														"physicalType": "String"
													},
													"sink": {
														"name": "MiddleName",
														"type": "String",
														"physicalType": "nvarchar"
													}
												},
												{
													"source": {
														"name": "LastName",
														"type": "String",
														"physicalType": "String"
													},
													"sink": {
														"name": "LastName",
														"type": "String",
														"physicalType": "nvarchar"
													}
												},
												{
													"source": {
														"name": "Suffix",
														"type": "String",
														"physicalType": "String"
													},
													"sink": {
														"name": "Suffix",
														"type": "String",
														"physicalType": "nvarchar"
													}
												},
												{
													"source": {
														"name": "CompanyName",
														"type": "String",
														"physicalType": "String"
													},
													"sink": {
														"name": "CompanyName",
														"type": "String",
														"physicalType": "nvarchar"
													}
												},
												{
													"source": {
														"name": "SalesPerson",
														"type": "String",
														"physicalType": "String"
													},
													"sink": {
														"name": "SalesPerson",
														"type": "String",
														"physicalType": "nvarchar"
													}
												},
												{
													"source": {
														"name": "EmailAddress",
														"type": "String",
														"physicalType": "String"
													},
													"sink": {
														"name": "EmailAddress",
														"type": "String",
														"physicalType": "nvarchar"
													}
												},
												{
													"source": {
														"name": "Phone",
														"type": "String",
														"physicalType": "String"
													},
													"sink": {
														"name": "Phone",
														"type": "String",
														"physicalType": "nvarchar"
													}
												},
												{
													"source": {
														"name": "PasswordHash",
														"type": "String",
														"physicalType": "String"
													},
													"sink": {
														"name": "PasswordHash",
														"type": "String",
														"physicalType": "varchar"
													}
												},
												{
													"source": {
														"name": "PasswordSalt",
														"type": "String",
														"physicalType": "String"
													},
													"sink": {
														"name": "PasswordSalt",
														"type": "String",
														"physicalType": "varchar"
													}
												},
												{
													"source": {
														"name": "rowguid",
														"type": "String",
														"physicalType": "String"
													},
													"sink": {
														"name": "rowguid",
														"type": "Guid",
														"physicalType": "uniqueidentifier"
													}
												}
											],
											"typeConversion": true,
											"typeConversionSettings": {
												"allowDataTruncation": true,
												"treatBooleanAsNumber": false
											}
										}
									},
									"inputs": [
										{
											"referenceName": "DelimitedText",
											"type": "DatasetReference",
											"parameters": {
												"filename": {
													"value": "@item().Name",
													"type": "Expression"
												}
											}
										}
									],
									"outputs": [
										{
											"referenceName": "ForEachDim",
											"type": "DatasetReference",
											"parameters": {}
										}
									]
								}
							]
						}
					},
					{
						"name": "GetMetadata",
						"type": "GetMetadata",
						"dependsOn": [],
						"policy": {
							"timeout": "0.12:00:00",
							"retry": 0,
							"retryIntervalInSeconds": 30,
							"secureOutput": false,
							"secureInput": false
						},
						"userProperties": [],
						"typeProperties": {
							"dataset": {
								"referenceName": "getcsvlist",
								"type": "DatasetReference",
								"parameters": {}
							},
							"fieldList": [
								"childItems"
							],
							"storeSettings": {
								"type": "AzureBlobFSReadSettings",
								"recursive": true,
								"enablePartitionDiscovery": false
							},
							"formatSettings": {
								"type": "DelimitedTextReadSettings"
							}
						}
					},
					{
						"name": "Storedprocedurecustlookup",
						"type": "SqlServerStoredProcedure",
						"dependsOn": [
							{
								"activity": "ForEachCustFile",
								"dependencyConditions": [
									"Succeeded"
								]
							}
						],
						"policy": {
							"timeout": "0.12:00:00",
							"retry": 0,
							"retryIntervalInSeconds": 30,
							"secureOutput": false,
							"secureInput": false
						},
						"userProperties": [],
						"typeProperties": {
							"storedProcedureName": "[[dbo].[GetCustomerDetails]",
							"storedProcedureParameters": {
								"CustomerID": {
									"value": "277",
									"type": "Int32"
								}
							}
						},
						"linkedServiceName": {
							"referenceName": "appdblinkedservice",
							"type": "LinkedServiceReference"
						}
					},
					{
						"name": "Lookup1",
						"type": "Lookup",
						"dependsOn": [
							{
								"activity": "Storedprocedurecustlookup",
								"dependencyConditions": [
									"Succeeded"
								]
							}
						],
						"policy": {
							"timeout": "0.12:00:00",
							"retry": 0,
							"retryIntervalInSeconds": 30,
							"secureOutput": false,
							"secureInput": false
						},
						"userProperties": [],
						"typeProperties": {
							"source": {
								"type": "AzureSqlSource",
								"sqlReaderStoredProcedureName": "[[dbo].[GetCustomerDetails]",
								"storedProcedureParameters": {
									"CustomerID": {
										"type": "Int32",
										"value": "277"
									}
								},
								"queryTimeout": "02:00:00",
								"partitionOption": "None"
							},
							"dataset": {
								"referenceName": "ForEachDim",
								"type": "DatasetReference",
								"parameters": {}
							},
							"firstRowOnly": true
						}
					},
					{
						"name": "SetCompanyNameVar",
						"type": "SetVariable",
						"dependsOn": [
							{
								"activity": "Lookup1",
								"dependencyConditions": [
									"Succeeded"
								]
							}
						],
						"policy": {
							"secureOutput": false,
							"secureInput": false
						},
						"userProperties": [],
						"typeProperties": {
							"variableName": "CompanyNameVar",
							"value": {
								"value": "@activity('Lookup1').output.firstRow.CompanyName",
								"type": "Expression"
							}
						}
					},
					{
						"name": "SetSalesPersonVar",
						"type": "SetVariable",
						"dependsOn": [
							{
								"activity": "Lookup1",
								"dependencyConditions": [
									"Succeeded"
								]
							}
						],
						"policy": {
							"secureOutput": false,
							"secureInput": false
						},
						"userProperties": [],
						"typeProperties": {
							"variableName": "SalesPersonVar",
							"value": {
								"value": "@activity('Lookup1').output['firstRow'].SalesPerson",
								"type": "Expression"
							}
						}
					}
				],
				"policy": {
					"elapsedTimeMetric": {}
				},
				"variables": {
					"CompanyNameVar": {
						"type": "String"
					},
					"SalesPersonVar": {
						"type": "String"
					}
				},
				"annotations": []
			},
			"dependsOn": []
		},
		{
			"name": "[concat(parameters('factoryName'), '/addCol pipeline')]",
			"type": "Microsoft.DataFactory/factories/pipelines",
			"apiVersion": "2018-06-01",
			"properties": {
				"activities": [
					{
						"name": "Copy parq to db_copy1",
						"type": "Copy",
						"dependsOn": [],
						"policy": {
							"timeout": "0.12:00:00",
							"retry": 0,
							"retryIntervalInSeconds": 30,
							"secureOutput": false,
							"secureInput": false
						},
						"userProperties": [],
						"typeProperties": {
							"source": {
								"type": "ParquetSource",
								"additionalColumns": [
									{
										"name": "FilePath",
										"value": "$$FILEPATH"
									},
									{
										"name": "RandomCol",
										"value": "$$COLUMN:Status"
									},
									{
										"name": "FileName",
										"value": "$$FILENAME"
									}
								],
								"storeSettings": {
									"type": "AzureBlobFSReadSettings",
									"recursive": true,
									"wildcardFileName": "*.parquet",
									"enablePartitionDiscovery": false
								},
								"formatSettings": {
									"type": "ParquetReadSettings"
								}
							},
							"sink": {
								"type": "AzureSqlSink",
								"writeBehavior": "insert",
								"sqlWriterUseTableLock": false
							},
							"enableStaging": false,
							"translator": {
								"type": "TabularTranslator",
								"mappings": [
									{
										"source": {
											"name": "Correlationid",
											"type": "String",
											"physicalType": "UTF8"
										},
										"sink": {
											"name": "Correlationid",
											"type": "String",
											"physicalType": "nvarchar"
										}
									},
									{
										"source": {
											"name": "Operationname",
											"type": "String",
											"physicalType": "UTF8"
										},
										"sink": {
											"name": "Operationname",
											"type": "String",
											"physicalType": "nvarchar"
										}
									},
									{
										"source": {
											"name": "Status",
											"type": "String",
											"physicalType": "UTF8"
										},
										"sink": {
											"name": "Status",
											"type": "String",
											"physicalType": "nvarchar"
										}
									},
									{
										"source": {
											"name": "Eventcategory",
											"type": "String",
											"physicalType": "UTF8"
										},
										"sink": {
											"name": "Eventcategory",
											"type": "String",
											"physicalType": "nvarchar"
										}
									},
									{
										"source": {
											"name": "Level",
											"type": "String",
											"physicalType": "UTF8"
										},
										"sink": {
											"name": "Level",
											"type": "String",
											"physicalType": "nvarchar"
										}
									},
									{
										"source": {
											"name": "Time",
											"type": "DateTime",
											"physicalType": "INT96"
										},
										"sink": {
											"name": "Time",
											"type": "DateTime",
											"physicalType": "datetime"
										}
									},
									{
										"source": {
											"name": "Subscription",
											"type": "String",
											"physicalType": "UTF8"
										},
										"sink": {
											"name": "Subscription",
											"type": "String",
											"physicalType": "nvarchar"
										}
									},
									{
										"source": {
											"name": "Eventinitiatedby",
											"type": "String",
											"physicalType": "UTF8"
										},
										"sink": {
											"name": "Eventinitiatedby",
											"type": "String",
											"physicalType": "nvarchar"
										}
									},
									{
										"source": {
											"name": "Resourcetype",
											"type": "String",
											"physicalType": "UTF8"
										},
										"sink": {
											"name": "Resourcetype",
											"type": "String",
											"physicalType": "nvarchar"
										}
									},
									{
										"source": {
											"name": "Resourcegroup",
											"type": "String",
											"physicalType": "UTF8"
										},
										"sink": {
											"name": "Resourcegroup",
											"type": "String",
											"physicalType": "nvarchar"
										}
									},
									{
										"source": {
											"name": "Resource",
											"type": "String",
											"physicalType": "UTF8"
										},
										"sink": {
											"name": "Resource",
											"type": "String",
											"physicalType": "nvarchar"
										}
									},
									{
										"source": {
											"name": "FilePath",
											"type": "String"
										},
										"sink": {
											"name": "FilePath",
											"type": "String",
											"physicalType": "nvarchar"
										}
									},
									{
										"source": {
											"name": "RandomCol",
											"type": "String"
										},
										"sink": {
											"name": "RandomCol",
											"type": "String",
											"physicalType": "nvarchar"
										}
									},
									{
										"source": {
											"name": "FileName",
											"type": "String"
										},
										"sink": {
											"name": "FileName",
											"type": "String",
											"physicalType": "nvarchar"
										}
									}
								],
								"typeConversion": true,
								"typeConversionSettings": {
									"allowDataTruncation": true,
									"treatBooleanAsNumber": false
								}
							}
						},
						"inputs": [
							{
								"referenceName": "LOGDATA_PARQUET",
								"type": "DatasetReference",
								"parameters": {}
							}
						],
						"outputs": [
							{
								"referenceName": "AzureSqlTableparquet",
								"type": "DatasetReference",
								"parameters": {}
							}
						]
					}
				],
				"policy": {
					"elapsedTimeMetric": {}
				},
				"annotations": [],
				"lastPublishTime": "2023-12-04T09:03:51Z"
			},
			"dependsOn": []
		},
		{
			"name": "[concat(parameters('factoryName'), '/csv to db adf-pipeline')]",
			"type": "Microsoft.DataFactory/factories/pipelines",
			"apiVersion": "2018-06-01",
			"properties": {
				"activities": [
					{
						"name": "Copy_90z",
						"type": "Copy",
						"dependsOn": [],
						"policy": {
							"timeout": "0.12:00:00",
							"retry": 0,
							"retryIntervalInSeconds": 30,
							"secureOutput": false,
							"secureInput": false
						},
						"userProperties": [
							{
								"name": "Source",
								"value": "csv//Log.csv"
							},
							{
								"name": "Destination",
								"value": "dbo.logdata"
							}
						],
						"typeProperties": {
							"source": {
								"type": "DelimitedTextSource",
								"storeSettings": {
									"type": "AzureBlobFSReadSettings",
									"recursive": true,
									"enablePartitionDiscovery": false
								},
								"formatSettings": {
									"type": "DelimitedTextReadSettings",
									"skipLineCount": 0
								}
							},
							"sink": {
								"type": "AzureSqlSink"
							},
							"enableStaging": false,
							"validateDataConsistency": false,
							"translator": {
								"type": "TabularTranslator",
								"mappings": [
									{
										"source": {
											"name": "Correlation id",
											"type": "String",
											"physicalType": "String"
										},
										"sink": {
											"name": "Correlation id",
											"type": "String",
											"physicalType": "nvarchar"
										}
									},
									{
										"source": {
											"name": "Operation name",
											"type": "String",
											"physicalType": "String"
										},
										"sink": {
											"name": "Operation name",
											"type": "String",
											"physicalType": "nvarchar"
										}
									},
									{
										"source": {
											"name": "Status",
											"type": "String",
											"physicalType": "String"
										},
										"sink": {
											"name": "Status",
											"type": "String",
											"physicalType": "nvarchar"
										}
									},
									{
										"source": {
											"name": "Event category",
											"type": "String",
											"physicalType": "String"
										},
										"sink": {
											"name": "Event category",
											"type": "String",
											"physicalType": "nvarchar"
										}
									},
									{
										"source": {
											"name": "Level",
											"type": "String",
											"physicalType": "String"
										},
										"sink": {
											"name": "Level",
											"type": "String",
											"physicalType": "nvarchar"
										}
									},
									{
										"source": {
											"name": "Time",
											"type": "String",
											"physicalType": "String"
										},
										"sink": {
											"name": "Time",
											"type": "String",
											"physicalType": "nvarchar"
										}
									},
									{
										"source": {
											"name": "Subscription",
											"type": "String",
											"physicalType": "String"
										},
										"sink": {
											"name": "Subscription",
											"type": "String",
											"physicalType": "nvarchar"
										}
									},
									{
										"source": {
											"name": "Event initiated by",
											"type": "String",
											"physicalType": "String"
										},
										"sink": {
											"name": "Event initiated by",
											"type": "String",
											"physicalType": "nvarchar"
										}
									},
									{
										"source": {
											"name": "Resource type",
											"type": "String",
											"physicalType": "String"
										},
										"sink": {
											"name": "Resource type",
											"type": "String",
											"physicalType": "nvarchar"
										}
									},
									{
										"source": {
											"name": "Resource group",
											"type": "String",
											"physicalType": "String"
										},
										"sink": {
											"name": "Resource group",
											"type": "String",
											"physicalType": "nvarchar"
										}
									},
									{
										"source": {
											"name": "Resource",
											"type": "String",
											"physicalType": "String"
										},
										"sink": {
											"name": "Resource",
											"type": "String",
											"physicalType": "nvarchar"
										}
									}
								],
								"typeConversion": true,
								"typeConversionSettings": {
									"allowDataTruncation": true,
									"treatBooleanAsNumber": false
								}
							}
						},
						"inputs": [
							{
								"referenceName": "SourceDataset_90z",
								"type": "DatasetReference",
								"parameters": {}
							}
						],
						"outputs": [
							{
								"referenceName": "DestinationDataset_90z",
								"type": "DatasetReference",
								"parameters": {}
							}
						]
					}
				],
				"policy": {
					"elapsedTimeMetric": {}
				},
				"annotations": [],
				"lastPublishTime": "2023-12-04T09:03:51Z"
			},
			"dependsOn": []
		},
		{
			"name": "[concat(parameters('factoryName'), '/metadatepipeline')]",
			"type": "Microsoft.DataFactory/factories/pipelines",
			"apiVersion": "2018-06-01",
			"properties": {
				"activities": [
					{
						"name": "GetMetadataCSV",
						"type": "GetMetadata",
						"dependsOn": [],
						"policy": {
							"timeout": "0.12:00:00",
							"retry": 0,
							"retryIntervalInSeconds": 30,
							"secureOutput": false,
							"secureInput": false
						},
						"userProperties": [],
						"typeProperties": {
							"dataset": {
								"referenceName": "DelimitedText1",
								"type": "DatasetReference",
								"parameters": {}
							},
							"fieldList": [
								"childItems",
								"itemName",
								"exists",
								"lastModified"
							],
							"storeSettings": {
								"type": "AzureBlobFSReadSettings",
								"recursive": true,
								"enablePartitionDiscovery": false
							},
							"formatSettings": {
								"type": "DelimitedTextReadSettings"
							}
						}
					},
					{
						"name": "GetMetadata-JSON",
						"type": "GetMetadata",
						"dependsOn": [
							{
								"activity": "GetMetadataCSV",
								"dependencyConditions": [
									"Succeeded"
								]
							}
						],
						"policy": {
							"timeout": "0.12:00:00",
							"retry": 0,
							"retryIntervalInSeconds": 30,
							"secureOutput": false,
							"secureInput": false
						},
						"userProperties": [],
						"typeProperties": {
							"dataset": {
								"referenceName": "arrajson",
								"type": "DatasetReference",
								"parameters": {}
							},
							"fieldList": [
								"childItems",
								"exists",
								"itemName",
								"lastModified"
							],
							"storeSettings": {
								"type": "AzureBlobFSReadSettings",
								"recursive": true,
								"enablePartitionDiscovery": false
							},
							"formatSettings": {
								"type": "JsonReadSettings"
							}
						}
					},
					{
						"name": "GetMetadataParquet",
						"type": "GetMetadata",
						"dependsOn": [
							{
								"activity": "GetMetadata-JSON",
								"dependencyConditions": [
									"Succeeded"
								]
							}
						],
						"policy": {
							"timeout": "0.12:00:00",
							"retry": 0,
							"retryIntervalInSeconds": 30,
							"secureOutput": false,
							"secureInput": false
						},
						"userProperties": [],
						"typeProperties": {
							"dataset": {
								"referenceName": "LOGDATA_PARQUET",
								"type": "DatasetReference",
								"parameters": {}
							},
							"fieldList": [
								"childItems",
								"exists",
								"itemName",
								"lastModified"
							],
							"storeSettings": {
								"type": "AzureBlobFSReadSettings",
								"recursive": true,
								"enablePartitionDiscovery": false
							},
							"formatSettings": {
								"type": "ParquetReadSettings"
							}
						}
					}
				],
				"policy": {
					"elapsedTimeMetric": {}
				},
				"variables": {
					"webhookvar": {
						"type": "String"
					}
				},
				"annotations": []
			},
			"dependsOn": []
		},
		{
			"name": "[concat(parameters('factoryName'), '/webhookpipeline')]",
			"type": "Microsoft.DataFactory/factories/pipelines",
			"apiVersion": "2018-06-01",
			"properties": {
				"activities": [
					{
						"name": "Webhook",
						"type": "WebActivity",
						"dependsOn": [],
						"policy": {
							"timeout": "0.12:00:00",
							"retry": 3,
							"retryIntervalInSeconds": 30,
							"secureOutput": false,
							"secureInput": false
						},
						"userProperties": [],
						"typeProperties": {
							"url": "https://datalakedemodp203.blob.core.windows.net/csv/Customer/Customer02.csv",
							"method": "GET",
							"headers": {}
						}
					},
					{
						"name": "copywebfilecsv",
						"type": "Copy",
						"dependsOn": [
							{
								"activity": "webhookvariable",
								"dependencyConditions": [
									"Succeeded"
								]
							}
						],
						"policy": {
							"timeout": "0.12:00:00",
							"retry": 0,
							"retryIntervalInSeconds": 30,
							"secureOutput": false,
							"secureInput": false
						},
						"userProperties": [],
						"typeProperties": {
							"source": {
								"type": "DelimitedTextSource",
								"additionalColumns": [
									{
										"name": "WebActvityOutput",
										"value": {
											"value": "{variables('webhookvar')}",
											"type": "Expression"
										}
									}
								],
								"storeSettings": {
									"type": "AzureBlobFSReadSettings",
									"recursive": true,
									"enablePartitionDiscovery": false
								},
								"formatSettings": {
									"type": "DelimitedTextReadSettings"
								}
							},
							"sink": {
								"type": "DelimitedTextSink",
								"storeSettings": {
									"type": "AzureBlobFSWriteSettings"
								},
								"formatSettings": {
									"type": "DelimitedTextWriteSettings",
									"quoteAllText": true,
									"fileExtension": ".txt"
								}
							},
							"enableStaging": false,
							"translator": {
								"type": "TabularTranslator",
								"mappings": [
									{
										"source": {
											"name": "WebActvityOutput",
											"type": "String"
										},
										"sink": {
											"name": "WebActvityOutput",
											"type": "String",
											"physicalType": "String"
										}
									}
								],
								"typeConversion": true,
								"typeConversionSettings": {
									"allowDataTruncation": true,
									"treatBooleanAsNumber": false
								}
							}
						},
						"inputs": [
							{
								"referenceName": "DelimitedText2",
								"type": "DatasetReference",
								"parameters": {}
							}
						],
						"outputs": [
							{
								"referenceName": "DelimitedText2",
								"type": "DatasetReference",
								"parameters": {}
							}
						]
					},
					{
						"name": "webhookvariable",
						"type": "SetVariable",
						"dependsOn": [
							{
								"activity": "Webhook",
								"dependencyConditions": [
									"Succeeded"
								]
							}
						],
						"policy": {
							"secureOutput": false,
							"secureInput": false
						},
						"userProperties": [],
						"typeProperties": {
							"variableName": "webhookvar",
							"value": {
								"value": "{activity('webhook').output.value[1]}",
								"type": "Expression"
							}
						}
					}
				],
				"policy": {
					"elapsedTimeMetric": {}
				},
				"variables": {
					"webhookvar": {
						"type": "String"
					}
				},
				"annotations": []
			},
			"dependsOn": []
		},
		{
			"name": "[concat(parameters('factoryName'), '/Binaryfileaccess')]",
			"type": "Microsoft.DataFactory/factories/datasets",
			"apiVersion": "2018-06-01",
			"properties": {
				"linkedServiceName": {
					"referenceName": "appvmserver",
					"type": "LinkedServiceReference"
				},
				"annotations": [],
				"type": "Binary",
				"typeProperties": {
					"location": {
						"type": "FileServerLocation",
						"fileName": "access.log"
					}
				}
			},
			"dependsOn": [
				"[concat(variables('factoryId'), '/linkedServices/appvmserver')]"
			]
		},
		{
			"name": "[concat(parameters('factoryName'), '/CreateDimTables')]",
			"type": "Microsoft.DataFactory/factories/dataflows",
			"apiVersion": "2018-06-01",
			"properties": {
				"type": "MappingDataFlow",
				"typeProperties": {
					"sources": [
						{
							"dataset": {
								"referenceName": "DelimitedText1",
								"type": "DatasetReference"
							},
							"name": "CustomerStream"
						},
						{
							"dataset": {
								"referenceName": "ProductTable",
								"type": "DatasetReference"
							},
							"name": "ProductStream"
						},
						{
							"dataset": {
								"referenceName": "ProductModelTable",
								"type": "DatasetReference"
							},
							"name": "ProductModelStream"
						},
						{
							"dataset": {
								"referenceName": "ProductCatTable",
								"type": "DatasetReference"
							},
							"name": "ProductCatStream"
						},
						{
							"dataset": {
								"referenceName": "CustomerTable",
								"type": "DatasetReference"
							},
							"name": "GETMAXCustomerSK"
						},
						{
							"dataset": {
								"referenceName": "DimProductable",
								"type": "DatasetReference"
							},
							"name": "DimProductLatest"
						},
						{
							"dataset": {
								"referenceName": "CustomerTable",
								"type": "DatasetReference"
							},
							"name": "DimCustomerLatest"
						}
					],
					"sinks": [
						{
							"dataset": {
								"referenceName": "CustomerTable",
								"type": "DatasetReference"
							},
							"name": "CustomerTableSink"
						},
						{
							"dataset": {
								"referenceName": "DimProductable",
								"type": "DatasetReference"
							},
							"name": "dimproductsink"
						},
						{
							"name": "MaxCustSKSink"
						}
					],
					"transformations": [
						{
							"name": "ProductTablejoinProductModel"
						},
						{
							"name": "ProductTablejoinProductCat"
						},
						{
							"name": "selectcolumns"
						},
						{
							"name": "surrogateproductKeystrea"
						},
						{
							"name": "selectcustcolumns"
						},
						{
							"name": "custsurrogateKeystream"
						},
						{
							"name": "derivedmaxskcust"
						},
						{
							"name": "duplicatecheckdimproduct"
						},
						{
							"name": "DoesCustomerExist"
						}
					],
					"scriptLines": [
						"source(output(",
						"          CustomerID as integer,",
						"          NameStyle as string,",
						"          Title as string,",
						"          FirstName as string,",
						"          MiddleName as string,",
						"          LastName as string,",
						"          Suffix as string,",
						"          CompanyName as string,",
						"          SalesPerson as string,",
						"          EmailAddress as string,",
						"          Phone as string,",
						"          PasswordHash as string,",
						"          PasswordSalt as string,",
						"          rowguid as string",
						"     ),",
						"     allowSchemaDrift: true,",
						"     validateSchema: false,",
						"     ignoreNoFilesFound: false) ~> CustomerStream",
						"source(output(",
						"          ProductID as integer,",
						"          Name as string,",
						"          ProductNumber as string,",
						"          Color as string,",
						"          StandardCost as decimal(19,4),",
						"          ListPrice as decimal(19,4),",
						"          Size as string,",
						"          Weight as decimal(8,2),",
						"          ProductCategoryID as integer,",
						"          ProductModelID as integer,",
						"          SellStartDate as timestamp,",
						"          SellEndDate as timestamp,",
						"          DiscontinuedDate as timestamp,",
						"          ThumbNailPhoto as binary,",
						"          ThumbnailPhotoFileName as string,",
						"          rowguid as string,",
						"          ModifiedDate as timestamp",
						"     ),",
						"     allowSchemaDrift: true,",
						"     validateSchema: false,",
						"     isolationLevel: 'READ_UNCOMMITTED',",
						"     format: 'table') ~> ProductStream",
						"source(output(",
						"          ProductModelID as integer,",
						"          Name as string,",
						"          CatalogDescription as string,",
						"          rowguid as string,",
						"          ModifiedDate as timestamp",
						"     ),",
						"     allowSchemaDrift: true,",
						"     validateSchema: false,",
						"     isolationLevel: 'READ_UNCOMMITTED',",
						"     format: 'table') ~> ProductModelStream",
						"source(output(",
						"          ProductCategoryID as integer,",
						"          ParentProductCategoryID as integer,",
						"          Name as string,",
						"          rowguid as string,",
						"          ModifiedDate as timestamp",
						"     ),",
						"     allowSchemaDrift: true,",
						"     validateSchema: false,",
						"     isolationLevel: 'READ_UNCOMMITTED',",
						"     format: 'table') ~> ProductCatStream",
						"source(output(",
						"          CustomerSK as integer",
						"     ),",
						"     allowSchemaDrift: true,",
						"     validateSchema: false,",
						"     isolationLevel: 'READ_UNCOMMITTED',",
						"     query: 'SELECT MAX([CustomerSK]) as CustomerSK FROM [dbo].[DimCustomer]\\n',",
						"     format: 'query') ~> GETMAXCustomerSK",
						"source(output(",
						"          ProductSK as integer,",
						"          ProductID as integer,",
						"          ProductModelID as integer,",
						"          ProductcategoryID as integer,",
						"          ProductName as string,",
						"          ProductModelName as string,",
						"          ProductCategoryName as string",
						"     ),",
						"     allowSchemaDrift: true,",
						"     validateSchema: false,",
						"     isolationLevel: 'READ_UNCOMMITTED',",
						"     format: 'table') ~> DimProductLatest",
						"source(output(",
						"          CustomerSK as integer,",
						"          CustomerID as integer,",
						"          CompanyName as string,",
						"          SalesPerson as string",
						"     ),",
						"     allowSchemaDrift: true,",
						"     validateSchema: false,",
						"     isolationLevel: 'READ_UNCOMMITTED',",
						"     format: 'table') ~> DimCustomerLatest",
						"duplicatecheckdimproduct, ProductModelStream join(ProductStream@ProductModelID == ProductModelStream@ProductModelID,",
						"     joinType:'left',",
						"     matchType:'exact',",
						"     ignoreSpaces: false,",
						"     broadcast: 'auto')~> ProductTablejoinProductModel",
						"ProductTablejoinProductModel, ProductCatStream join(ProductStream@ProductCategoryID == ProductCatStream@ProductCategoryID,",
						"     joinType:'left',",
						"     matchType:'exact',",
						"     ignoreSpaces: false,",
						"     broadcast: 'auto')~> ProductTablejoinProductCat",
						"ProductTablejoinProductCat select(mapColumn(",
						"          ProductID,",
						"          ProductName = ProductStream@Name,",
						"          ProductCategoryID = ProductStream@ProductCategoryID,",
						"          ProductModelID = ProductStream@ProductModelID,",
						"          ProductModelName = ProductModelStream@Name,",
						"          ProductCategoryName = ProductCatStream@Name",
						"     ),",
						"     skipDuplicateMapInputs: true,",
						"     skipDuplicateMapOutputs: true) ~> selectcolumns",
						"selectcolumns keyGenerate(output(ProductSK as long),",
						"     startAt: 1L,",
						"     stepValue: 1L) ~> surrogateproductKeystrea",
						"DoesCustomerExist select(mapColumn(",
						"          CustomerID,",
						"          CompanyName,",
						"          SalesPerson",
						"     ),",
						"     skipDuplicateMapInputs: true,",
						"     skipDuplicateMapOutputs: true) ~> selectcustcolumns",
						"selectcustcolumns keyGenerate(output(CustomerSK as long),",
						"     startAt: 1L,",
						"     stepValue: 1L) ~> custsurrogateKeystream",
						"custsurrogateKeystream derive(CustomerSK = CustomerSK + MaxCustSKSink#outputs()[1].CustomerSK) ~> derivedmaxskcust",
						"ProductStream, DimProductLatest exists(ProductStream@ProductID == DimProductLatest@ProductID,",
						"     negate:true,",
						"     broadcast: 'auto')~> duplicatecheckdimproduct",
						"CustomerStream, DimCustomerLatest exists(CustomerStream@CustomerID == DimCustomerLatest@CustomerID,",
						"     negate:true,",
						"     broadcast: 'auto')~> DoesCustomerExist",
						"derivedmaxskcust sink(allowSchemaDrift: true,",
						"     validateSchema: false,",
						"     input(",
						"          CustomerSK as integer,",
						"          CustomerID as integer,",
						"          CompanyName as string,",
						"          SalesPerson as string",
						"     ),",
						"     deletable:false,",
						"     insertable:true,",
						"     updateable:false,",
						"     upsertable:false,",
						"     format: 'table',",
						"     skipDuplicateMapInputs: true,",
						"     skipDuplicateMapOutputs: true,",
						"     errorHandlingOption: 'stopOnFirstError',",
						"     mapColumn(",
						"          CustomerSK,",
						"          CustomerID,",
						"          CompanyName,",
						"          SalesPerson",
						"     )) ~> CustomerTableSink",
						"surrogateproductKeystrea sink(allowSchemaDrift: true,",
						"     validateSchema: false,",
						"     input(",
						"          ProductSK as integer,",
						"          ProductID as integer,",
						"          ProductModelID as integer,",
						"          ProductcategoryID as integer,",
						"          ProductName as string,",
						"          ProductModelName as string,",
						"          ProductCategoryName as string",
						"     ),",
						"     deletable:false,",
						"     insertable:true,",
						"     updateable:false,",
						"     upsertable:false,",
						"     format: 'table',",
						"     skipDuplicateMapInputs: true,",
						"     skipDuplicateMapOutputs: true,",
						"     errorHandlingOption: 'stopOnFirstError',",
						"     mapColumn(",
						"          ProductSK,",
						"          ProductID,",
						"          ProductModelID,",
						"          ProductcategoryID = ProductCategoryID,",
						"          ProductName,",
						"          ProductModelName,",
						"          ProductCategoryName",
						"     )) ~> dimproductsink",
						"GETMAXCustomerSK sink(validateSchema: false,",
						"     skipDuplicateMapInputs: true,",
						"     skipDuplicateMapOutputs: true,",
						"     store: 'cache',",
						"     format: 'inline',",
						"     output: false,",
						"     saveOrder: 1,",
						"     mapColumn(",
						"          CustomerSK",
						"     )) ~> MaxCustSKSink"
					]
				}
			},
			"dependsOn": []
		},
		{
			"name": "[concat(parameters('factoryName'), '/binarydataflow')]",
			"type": "Microsoft.DataFactory/factories/dataflows",
			"apiVersion": "2018-06-01",
			"properties": {
				"type": "MappingDataFlow",
				"typeProperties": {
					"sources": [
						{
							"dataset": {
								"referenceName": "binaryText",
								"type": "DatasetReference"
							},
							"name": "binarysource"
						}
					],
					"sinks": [
						{
							"dataset": {
								"referenceName": "binarytable",
								"type": "DatasetReference"
							},
							"name": "binarysink"
						}
					],
					"transformations": [
						{
							"name": "selectbinarycolumns"
						},
						{
							"name": "timelocaltransformation"
						}
					],
					"scriptLines": [
						"source(output(",
						"          Column_1 as string,",
						"          Column_2 as string,",
						"          Column_3 as string,",
						"          Column_4 as string,",
						"          Column_5 as string,",
						"          Column_6 as string,",
						"          Column_7 as string,",
						"          Column_8 as string,",
						"          Column_9 as string,",
						"          Column_10 as string",
						"     ),",
						"     allowSchemaDrift: true,",
						"     validateSchema: false,",
						"     ignoreNoFilesFound: false) ~> binarysource",
						"binarysource select(mapColumn(",
						"          Remote_addr = Column_1,",
						"          Time_local = Column_4,",
						"          Request = Column_6,",
						"          Status = Column_7,",
						"          Bytes = Column_8",
						"     ),",
						"     skipDuplicateMapInputs: true,",
						"     skipDuplicateMapOutputs: true) ~> selectbinarycolumns",
						"selectbinarycolumns derive(Time_local = substring((Time_local),2,length(Time_local)-1)) ~> timelocaltransformation",
						"timelocaltransformation sink(allowSchemaDrift: true,",
						"     validateSchema: false,",
						"     input(",
						"          Remote_addr as string,",
						"          Time_local as string,",
						"          Request as string,",
						"          Status as integer,",
						"          Bytes as integer",
						"     ),",
						"     deletable:false,",
						"     insertable:true,",
						"     updateable:false,",
						"     upsertable:false,",
						"     format: 'table',",
						"     skipDuplicateMapInputs: true,",
						"     skipDuplicateMapOutputs: true,",
						"     errorHandlingOption: 'stopOnFirstError',",
						"     mapColumn(",
						"          Remote_addr,",
						"          Time_local,",
						"          Request,",
						"          Status,",
						"          Bytes",
						"     )) ~> binarysink"
					]
				}
			},
			"dependsOn": []
		}
	]
}